symmstate/__init__.py
symmstate/__main__.py
symmstate/_symm_state_core.py
symmstate/cli.py
symmstate/unit_cell_module.py
symmstate/abinit/__init__.py
symmstate/abinit/abinit_file.py
symmstate/abinit/abinit_unit_cell.py
symmstate/config/__init__.py
symmstate/config/symm_state_settings.py
symmstate/flpz/__init__.py
symmstate/flpz/data_analysis.py
symmstate/flpz/flpz_core.py
symmstate/flpz/perturbations.py
symmstate/flpz/smodes_processor.py
symmstate/flpz/coupling/__init__.py
symmstate/flpz/coupling/coupling_program.py
symmstate/flpz/electrotensor/__init__.py
symmstate/flpz/electrotensor/electro_tensor_program.py
symmstate/flpz/energy/__init__.py
symmstate/flpz/energy/energy_program.py
symmstate/polynomial_fitting/polynomialFitting2D.py
symmstate/polynomial_fitting/polynomialFitting2D3D.py
symmstate/polynomial_fitting/polynomialFitting3D.py
symmstate/polynomial_fitting/polynomialFitting3DView.py
symmstate/pseudopotentials/__init__.py
symmstate/pseudopotentials/pseudopotential_manager.py
symmstate/slurm/__init__.py
symmstate/slurm/slurm_file.py
symmstate/slurm/slurm_header.py
symmstate/templates/__init__.py
symmstate/templates/template_manager.py
symmstate/utils/__init__.py
symmstate/utils/abinit_parser.py
symmstate/utils/data_parser.py
symmstate/utils/documentation.py
symmstate/utils/exceptions.py
symmstate/utils/file_io.py
symmstate/utils/logger.py
symmstate/utils/misc.py
symmstate/utils/numerical.py
symmstate/utils/paths.py
symmstate/utils/symmetry_adapted_basis.py
symmstate/vasp/__init__.py
symmstate/vasp/vasp_convergence_file.py
symmstate/vasp/vasp_unit_cell.py
symmstate-0.9.11.dist-info/licenses/LICENSE
symmstate-0.9.11.dist-info/METADATA
symmstate-0.9.11.dist-info/WHEEL
symmstate-0.9.11.dist-info/entry_points.txt
symmstate-0.9.11.dist-info/top_level.txt
symmstate-0.9.11.dist-info/RECORD
