Metadata-Version: 2.4
Name: symmstate
Version: 0.9.11
Summary: Solid-state Physics Package for Symmetry Based Calculations!
Home-page: https://github.com/isaac-perez7053
Author: Isaac Perez
Author-email: Isaac Perez <iperez@g.hmc.edu>
Classifier: Development Status :: 4 - Beta
Classifier: Programming Language :: Python :: 3
Classifier: License :: OSI Approved :: MIT License
Classifier: Intended Audience :: Science/Research
Classifier: Topic :: Scientific/Engineering :: Chemistry
Classifier: Topic :: Scientific/Engineering :: Physics
Requires-Python: >=3.8
License-File: LICENSE
Requires-Dist: pymatgen>=2023.7.20
Requires-Dist: numpy>=1.21
Requires-Dist: scipy>=1.7
Requires-Dist: pyyaml>=6.0
Requires-Dist: click>=8.0
Requires-Dist: matplotlib>=3.5
Provides-Extra: dev
Requires-Dist: black>=22.3; extra == "dev"
Dynamic: license-file
